tests/__init__.py
tests/mock.py
tests/test_functions.py
tests/test_token.py
tests/test_url.py
vetmanager/__init__.py
vetmanager/functions.py
vetmanager/token.py
vetmanager/url.py
py_vetmanager_api-0.2.2.dist-info/LICENSE
py_vetmanager_api-0.2.2.dist-info/METADATA
py_vetmanager_api-0.2.2.dist-info/WHEEL
py_vetmanager_api-0.2.2.dist-info/top_level.txt
py_vetmanager_api-0.2.2.dist-info/RECORD
