Metadata-Version: 2.1
Name: py-vetmanager-api
Version: 0.2.2
Summary: UNKNOWN
Home-page: https://github.com/otis22/PyVetmanagerApi
Author: otis
Author-email: vromanichev24@gmail.com
License: MIT
Platform: UNKNOWN
Requires-Dist: requests
